README.md
setup.py
warna/__init__.py
warna/warna.py
warna.egg-info/PKG-INFO
warna.egg-info/SOURCES.txt
warna.egg-info/dependency_links.txt
warna.egg-info/top_level.txt