Metadata-Version: 2.1
Name: warna
Version: 1.1.3
Summary: Menambahkan warna di Terminal
Home-page: https://github.com/mzaini30/warna
Author: Zen
Author-email: muhzaini30@gmail.com
License: UNKNOWN
Project-URL: Bug Tracker, https://github.com/mzaini30/warna/issues
Platform: UNKNOWN
Classifier: Programming Language :: Python :: 3
Classifier: License :: OSI Approved :: MIT License
Classifier: Operating System :: OS Independent
